khu_llm_toolkit/__init__.py
khu_llm_toolkit/commons.py
khu_llm_toolkit/config.ini.sample
khu_llm_toolkit/model_definition.py
khu_llm_toolkit-0.1.9.dist-info/LICENSE
khu_llm_toolkit-0.1.9.dist-info/LICENSE.txt
khu_llm_toolkit-0.1.9.dist-info/METADATA
khu_llm_toolkit-0.1.9.dist-info/WHEEL
khu_llm_toolkit-0.1.9.dist-info/RECORD
