Metadata-Version: 2.1
Name: khu-llm-toolkit
Version: 0.1.9
Summary: 
Author: Ken Hu
Author-email: ken.hu@hwacom.com
Requires-Python: >=3.9,<4.0
Classifier: Programming Language :: Python :: 3
Classifier: Programming Language :: Python :: 3.9
Classifier: Programming Language :: Python :: 3.10
Classifier: Programming Language :: Python :: 3.11
Classifier: Programming Language :: Python :: 3.12
Requires-Dist: langchain (==0.3.0)
Requires-Dist: langchain-community (==0.3.0)
Requires-Dist: langchain-google-genai (==2.0.0)
Requires-Dist: langchain-openai (==0.2.0)
Requires-Dist: llama-index-embeddings-azure-openai (==0.2.5)
Requires-Dist: llama-index-embeddings-openai (==0.2.5)
Requires-Dist: llama-index-llms-azure-openai (==0.2.1)
Requires-Dist: llama-index-llms-openai (==0.2.9)
Requires-Dist: pytest (>=8.0.0,<9.0.0)
